setup.py
salure_helpers/planday/__init__.py
salure_helpers/planday/planday.py
salure_helpers_planday.egg-info/PKG-INFO
salure_helpers_planday.egg-info/SOURCES.txt
salure_helpers_planday.egg-info/dependency_links.txt
salure_helpers_planday.egg-info/not-zip-safe
salure_helpers_planday.egg-info/requires.txt
salure_helpers_planday.egg-info/top_level.txt