Metadata-Version: 1.0
Name: salure-helpers-planday
Version: 0.0.3
Summary: Planday wrapper from Salure
Home-page: UNKNOWN
Author: D&A Salure
Author-email: support@salureconnnect.com
License: Salure License
Platform: UNKNOWN
